Workbook
Name Дней_макс: Справочники!$L$7
Name Дней_макс_скидка: Справочники!$L$6
Name Дней_мин: Справочники!$L$4
Name Дней_мин_скидка: Справочники!$L$3
Name Дней_не_менее: Справочники!$H$4
Name Комнаты: Справочники!$A$2:$B$16
Name Курс_доллара: Справочники!$H$1
Name Номера_комнат: Справочники!$A$2:$A$16
Name Скидка: Справочники!$H$3
Name Цены: Справочники!$D$2:$E$4

Sheet Лист1
A1: Исходные данные
A2: a = | B2: 2.75
A3: b = | B3: 1.3
A4: x = | B4: -7.85
A5: d = | B5: 1.23
A6: k = | B6: -2
A7: Вычисление формулы
A8: =10^4*SQRT(B2^2*B3^2)/(B4^2+B2^2)-1.7*SQRT(7)*(B2^2+B3^2)/((B2+B3)*B6*B5)-COS(2)/ABS(B4+B5+B6) -> 520.95581

Sheet Лист2
A1: № | B1: Фамилия И.О. | C1: Оценки
C2: Математика | F2: Информатика | I2: Физика
C3: I | D3: II | E3: год | F3: I | G3: II | H3: год | I3: I | J3: II | K3: год
A4: 1 | B4: Садеков Д.Р. | C4: 5 | D4: 5 | E4: 5 | F4: 5 | G4: 5 | H4: 5 | I4: 4 | J4: 5 | K4: 5
A5: 2 | B5: Езерский И.К | C5: 5 | D5: 5 | E5: 5 | F5: 5 | G5: 5 | H5: 5 | I5: 4 | J5: 4 | K5: 4
A6: 3 | B6: Петренко А.А. | C6: 5 | D6: 5 | E6: 5 | F6: 5 | G6: 5 | H6: 5 | I6: 5 | J6: 5 | K6: 5
A7: 4 | B7: Сусликов Д.Б. | C7: 5 | D7: 5 | E7: 4 | F7: 4 | G7: 3 | H7: 2 | I7: 3 | J7: 3 | K7: 4
A8: 5 | B8: Аргинов Т.Т. | C8: 3 | D8: 4 | E8: 2 | F8: 5 | G8: 4 | H8: 3 | I8: 2 | J8: 3 | K8: 2
A9: 6 | B9: Фугасов А.Э. | C9: 3 | D9: 3 | E9: 3 | F9: 3 | G9: 3 | H9: 4 | I9: 5 | J9: 2 | K9: 3
A10: 7 | B10: Смирнов. Н.А. | C10: 2 | D10: 3 | E10: 4 | F10: 3 | G10: 2 | H10: 3 | I10: 2 | J10: 2 | K10: 2
A11: 8 | B11: Батуев З.В. | C11: 3 | D11: 4 | E11: 2 | F11: 5 | G11: 2 | H11: 3 | I11: 4 | J11: 2 | K11: 4
A12: 9 | B12: Параходов В.Е. | C12: 3 | D12: 2 | E12: 3 | F12: 2 | G12: 4 | H12: 5 | I12: 4 | J12: 5 | K12: 4
A13: 10 | B13: Юнитович Е.А. | C13: 4 | D13: 4 | E13: 4 | F13: 4 | G13: 4 | H13: 4 | I13: 4 | J13: 4 | K13: 4
B14: Итого "5" | C14: =COUNTIF(C$4:C$13,5) -> 4 | D14: =COUNTIF(D$4:D$13,5) -> 4 | E14: =COUNTIF(E$4:E$13,5) -> 3 | F14: =COUNTIF(F$4:F$13,5) -> 5 | G14: =COUNTIF(G$4:G$13,5) -> 3 | H14: =COUNTIF(H$4:H$13,5) -> 4 | I14: =COUNTIF(I$4:I$13,5) -> 2 | J14: =COUNTIF(J$4:J$13,5) -> 3 | K14: =COUNTIF(K$4:K$13,5) -> 2
B15: Итого "4" | C15: =COUNTIF(C$4:C$13,4) -> 1 | D15: =COUNTIF(D$4:D$13,4) -> 3 | E15: =COUNTIF(E$4:E$13,4) -> 3 | F15: =COUNTIF(F$4:F$13,4) -> 2 | G15: =COUNTIF(G$4:G$13,4) -> 3 | H15: =COUNTIF(H$4:H$13,4) -> 2 | I15: =COUNTIF(I$4:I$13,4) -> 5 | J15: =COUNTIF(J$4:J$13,4) -> 2 | K15: =COUNTIF(K$4:K$13,4) -> 5
B16: Итого "3" | C16: =COUNTIF(C$4:C$13,3) -> 4 | D16: =COUNTIF(D$4:D$13,3) -> 2 | E16: =COUNTIF(E$4:E$13,3) -> 2 | F16: =COUNTIF(F$4:F$13,3) -> 2 | G16: =COUNTIF(G$4:G$13,3) -> 2 | H16: =COUNTIF(H$4:H$13,3) -> 3 | I16: =COUNTIF(I$4:I$13,3) -> 1 | J16: =COUNTIF(J$4:J$13,3) -> 2 | K16: =COUNTIF(K$4:K$13,3) -> 1
B17: Итого "2" | C17: =COUNTIF(C$4:C$13,2) -> 1 | D17: =COUNTIF(D$4:D$13,2) -> 1 | E17: =COUNTIF(E$4:E$13,2) -> 2 | F17: =COUNTIF(F$4:F$13,2) -> 1 | G17: =COUNTIF(G$4:G$13,2) -> 2 | H17: =COUNTIF(H$4:H$13,2) -> 1 | I17: =COUNTIF(I$4:I$13,2) -> 2 | J17: =COUNTIF(J$4:J$13,2) -> 3 | K17: 4

Sheet Лист3
A1: БИРЖА ТРУДА
A2: Контингент | B2: 2007 год | C2: 2008 год | D2: 2009 год | E2: 2010 год | F2: 2011 год
A3: Учащиеся | B3: 623 | C3: 2465 | D3: 1500 | E3: 1300 | F3: 2850
A4: Студенты | B4: 1250 | C4: 3500 | D4: 2500 | E4: 1800 | F4: 2150
A5: Высшее образование | B5: 2560 | C5: 930 | D5: 1300 | E5: 1120 | F5: 2510
A6: Среднее- профессиональное образование | B6: 850 | C6: 2500 | D6: 1200 | E6: 1800 | F6: 1650
A7: Рабочие | B7: 1456 | F7: 1250
A8: Другие | B8: 980 | C8: 1450 | D8: 1200 | E8: 560 | F8: 850

Sheet Лаб3 1
A1: № | B1: Название фирмы | C1: Специализация | D1: Дата счёта | E1: Сумма в счёте
A2: 1 | B2: ОАО "Райн Гослинг" | C2: Общественный транспорт | D2: 39114 | E2: 10800
A3: 2 | B3: ООО "Удивление" | C3: Цветы | D3: 39299 | E3: 20000
A4: 3 | B4: ТОО "ЭТО" | C4: Авто - транспорт | D4: 39406 | E4: 43000
A5: 4 | B5: ЗАО "ПАО" | C5: Кино производство | D5: 39128 | E5: 18000
A6: 5 | B6: ЗАО "СОСАГЕ" | C6: Сосательные изделия | D6: 39326 | E6: 47000
A7: 6 | B7: ООО "кЕтчунез" | C7: Продуктовые изделия | D7: 39202 | E7: 30720
A8: 7 | B8: ООО "GOSLING" | C8: Автомобили | D8: 39264 | E8: 80991
A9: 8 | B9: ТОО "Cё" | C9: Строительсво | D9: 39299 | E9: 30234
A10: 9 | B10: ЗАО "Зигрит" | C10: Табачные изделия | D10: 39406 | E10: 11000
A11: 10 | B11: ЗАО "Культурная революция" | C11: Продуктовые изделия | D11: 39128 | E11: 15664

Sheet Лаб3 2
A1: № | B1: Название фирмы | C1: Специализация | D1: Дата счёта | E1: Сумма в счёте | N1: № | O1: Название фирмы | P1: Специализация | Q1: Дата счёта | R1: Сумма в счёте | T1: Название фирмы
A2: 1 | B2: ОАО "Райн Гослинг" | C2: Общественный транспорт | D2: 39114 | E2: 10800 | G2: Сумма в счёте | H2: Сумма в счёте | N2: 1 | O2: ОАО "Райн Гослинг" | P2: Общественный транспорт | Q2: 39114 | R2: 10800 | T2: ОАО*
A3: 2 | B3: ООО "Удивление" | C3: Цветы | D3: 39299 | E3: 20000 | G3: >50000 | H3: <=90000 | N3: 2 | O3: ООО "Удивление" | P3: Цветы | Q3: 39299 | R3: 20000
A4: 3 | B4: ТОО "ЭТО" | C4: Авто - транспорт | D4: 39406 | E4: 94005 | N4: 3 | O4: ТОО "ЭТО" | P4: Авто - транспорт | Q4: 39406 | R4: 94005 | T4: Специализация
A5: 4 | B5: ЗАО "ПАО" | C5: Кино производство | D5: 39128 | E5: 18000 | G5: Сумма в счёте | H5: Дата счёта | N5: 4 | O5: ЗАО "ПАО" | P5: Кино производство | Q5: 39128 | R5: 18000 | T5: Общественный транспорт
A6: 5 | B6: ЗАО "СОСАГЕ" | C6: Сосательные изделия | D6: 39326 | E6: 47000 | G6: >=30000 | H6: >=20.04.2007 | N6: 5 | O6: ЗАО "СОСАГЕ" | P6: Сосательные изделия | Q6: 39326 | R6: 47000 | T6: Цветы
A7: 6 | B7: ООО "кЕтчунез" | C7: Продуктовые изделия | D7: 39202 | E7: 50650 | N7: 6 | O7: ООО "кЕтчунез" | P7: Продуктовые изделия | Q7: 39202 | R7: 50650
A8: 7 | B8: ООО "GOSLING" | C8: Автомобили | D8: 39264 | E8: 80991 | G8: Специализация | H8: Дата счёта | I8: Сумма в счёте | N8: 7 | O8: ООО "GOSLING" | P8: Автомобили | Q8: 39264 | R8: 80991
A9: 8 | B9: ТОО "Cё" | C9: Строительсво | D9: 39299 | E9: 30234 | G9: Общественный транспорт* | H9: <01.07.2007 | I9: <=20000 | N9: 8 | O9: ТОО "Cё" | P9: Строительсво | Q9: 39299 | R9: 30234
A10: 9 | B10: ЗАО "Зигрит" | C10: Табачные изделия | D10: 39406 | E10: 110000 | N10: 9 | O10: ЗАО "Зигрит" | P10: Табачные изделия | Q10: 39406 | R10: 110000
A11: 10 | B11: ЗАО "Культурная революция" | C11: Продуктовые изделия | D11: 39128 | E11: 15664 | G11: Специализация
G12: Продуктовые изделия | N12: № | O12: Название фирмы | P12: Специализация | Q12: Дата счёта | R12: Сумма в счёте
B13: Название фирмы | C13: Специализация | G13: Кино производство | N13: 1 | O13: ОАО "Райн Гослинг" | P13: Общественный транспорт | Q13: 39114 | R13: 10800
B14: ООО "кЕтчунез" | C14: Продуктовые изделия
B15: ООО "GOSLING" | C15: Автомобили | G15: Сумма выше среднего
G16: =E2>AVERAGE($E$2:$E$11) -> FALSE | N16: № | O16: Название фирмы | P16: Специализация | Q16: Дата счёта | R16: Сумма в счёте
B17: Название фирмы | C17: Сумма в счёте | D17: Дата счёта | N17: 1 | O17: ОАО "Райн Гослинг" | P17: Общественный транспорт | Q17: 39114 | R17: 10800
B18: ТОО "ЭТО" | C18: 94005 | D18: 39406 | G18: Название фирмы | N18: 2 | O18: ООО "Удивление" | P18: Цветы | Q18: 39299 | R18: 20000
B19: ЗАО "СОСАГЕ" | C19: 47000 | D19: 39326 | G19: ООО*
B20: ООО "кЕтчунез" | C20: 50650 | D20: 39202
B21: ООО "GOSLING" | C21: 80991 | D21: 39264 | G21: Общая сумма в счёте
B22: ТОО "Cё" | C22: 30234 | D22: 39299 | G22: =DSUM(A1:E11,E1,G18:G19) -> 151641
B23: ЗАО "Зигрит" | C23: 110000 | D23: 39406
G24: Сумма в счёте
B25: Название фирмы | C25: Специализация | D25: Дата счёта | E25: Сумма в счёте | G25: <20000
B26: ОАО "Райн Гослинг" | C26: Общественный транспорт | D26: 39114 | E26: 10800
G27: Количество фирм
B28: Название фирмы | C28: Специализация | D28: Сумма в счёте | G28: =DCOUNT(A1:E11,E1,G24:G25) -> 3
B29: ЗАО "ПАО" | C29: Кино производство | D29: 18000
B30: ООО "кЕтчунез" | C30: Продуктовые изделия | D30: 50650 | G30: Название фирмы
B31: ЗАО "Культурная революция" | C31: Продуктовые изделия | D31: 15664 | G31: ЗАО*
G33: Минимальная сумма
G34: =DMIN(A1:E11,E1,G30:G31) -> 15664
G36: Название фирмы
G37: ТОО*
G39: Максимальная сумма
G40: =DMAX(A1:E11,E1,G36:G37) -> 94005

Sheet Лаб3 3
A1: N | B1: Фамилия | C1: Имя | D1: Класс | E1: Год рожд. | F1: Число пропусков | G1: Число посещенных занятий
A2: 1 | B2: Ершова | C2: Елена | D2: 9 | E2: 1997 | F2: 2 | G2: 34 | I2: Класс | J2: Число пропусков
A3: 2 | B3: Петров | C3: Александр | D3: 10 | E3: 1997 | F3: 6 | G3: 30 | I3: =10 -> 10 | J3: >5
A4: 3 | B4: Сидоров | C4: Василий | D4: 11 | E4: 1996 | F4: 6 | G4: 30
A5: 4 | B5: Козлов | C5: Денис | D5: 10 | E5: 1997 | F5: 12 | G5: 24
A6: 5 | B6: Симонова | C6: Юлия | D6: 10 | E6: 1997 | F6: 8 | G6: 28
A7: 6 | B7: Петров | C7: Алексей | D7: 9 | E7: 1998 | F7: 3 | G7: 33
A8: 7 | B8: Борисов | C8: Петр | D8: 10 | E8: 1997 | F8: 12 | G8: 24
A9: 8 | B9: Морозова | C9: Екатерина | D9: 10 | E9: 1997 | F9: 6 | G9: 30
A10: 9 | B10: Петров | C10: Василия | D10: 9 | E10: 1998 | F10: 9 | G10: 27
A11: 10 | B11: Громов | C11: Андрей | D11: 10 | E11: 1997 | F11: 4 | G11: 32
A12: 11 | B12: Алферова | C12: Мария | D12: 9 | E12: 1998 | F12: 10 | G12: 26
A13: 12 | B13: Козлов | C13: Семен | D13: 11 | E13: 1996 | F13: 8 | G13: 28
A14: 13 | B14: Симонова | C14: Валентина | D14: 10 | E14: 1997 | F14: 8 | G14: 28
A15: 14 | B15: Симонова | C15: Ирина | D15: 11 | E15: 1996 | F15: 1 | G15: 35
A17: N | B17: Фамилия | C17: Имя | D17: Класс | E17: Год рожд. | F17: Число пропусков | G17: Число посещенных занятий
A18: 2 | B18: Петров | C18: Александр | D18: 10 | E18: 1997 | F18: 6 | G18: 30
A19: 4 | B19: Козлов | C19: Денис | D19: 10 | E19: 1997 | F19: 12 | G19: 24
A20: 5 | B20: Симонова | C20: Юлия | D20: 10 | E20: 1997 | F20: 8 | G20: 28
A21: 7 | B21: Борисов | C21: Петр | D21: 10 | E21: 1997 | F21: 12 | G21: 24
A22: 8 | B22: Морозова | C22: Екатерина | D22: 10 | E22: 1997 | F22: 6 | G22: 30
A23: 13 | B23: Симонова | C23: Валентина | D23: 10 | E23: 1997 | F23: 8 | G23: 28
A25: N | B25: Фамилия | C25: Имя | D25: Класс | E25: Год рожд. | F25: Число пропусков | G25: Число посещенных занятий
A26: 1 | B26: Ершова | C26: Елена | D26: 9 | E26: 1997 | F26: 2 | G26: 34
A27: 2 | B27: Петров | C27: Александр | D27: 10 | E27: 1997 | F27: 6 | G27: 30
A28: 3 | B28: Сидоров | C28: Василий | D28: 11 | E28: 1996 | F28: 6 | G28: 30
A29: 4 | B29: Козлов | C29: Денис | D29: 10 | E29: 1997 | F29: 12 | G29: 24
A30: 5 | B30: Симонова | C30: Юлия | D30: 10 | E30: 1997 | F30: 8 | G30: 28
A31: 6 | B31: Петров | C31: Алексей | D31: 9 | E31: 1998 | F31: 3 | G31: 33
A32: 7 | B32: Борисов | C32: Петр | D32: 10 | E32: 1997 | F32: 12 | G32: 24
A33: 8 | B33: Морозова | C33: Екатерина | D33: 10 | E33: 1997 | F33: 6 | G33: 30
A34: 9 | B34: Петров | C34: Василия | D34: 9 | E34: 1998 | F34: 9 | G34: 27
A35: 10 | B35: Громов | C35: Андрей | D35: 10 | E35: 1997 | F35: 4 | G35: 32
A36: 11 | B36: Алферова | C36: Мария | D36: 9 | E36: 1998 | F36: 10 | G36: 26
A37: 12 | B37: Козлов | C37: Семен | D37: 11 | E37: 1996 | F37: 8 | G37: 28
... A39: 14 | B39: Симонова | C39: Ирина | D39: 11 | E39: 1996 | F39: 1 | G39: 35

Sheet Лист5
A1: Менеджер | B1: Месяц | C1: Продукты | D1: Доход | E1: Расход | F1: Прибыль | G1: Регион
A2: Иванов | B2: январь | C2: мясо | D2: 100 | E2: 50 | F2: =D2-E2 -> 50 | G2: Страны СНГ | I2: Регион | J2: (Все)
A3: Иванов | B3: февраль | C3: мясо | D3: 100 | E3: 50 | F3: =D3-E3 -> 50 | G3: Россия
A4: Иванов | B4: февраль | C4: мясо | D4: 100 | E4: 50 | F4: =D4-E4 -> 50 | G4: Россия | I4: Сумма по полю Прибыль | K4: Месяц
A5: Иванов | B5: апрель | C5: мясо | D5: 100 | E5: 50 | F5: =D5-E5 -> 50 | G5: Россия | I5: Продукты | J5: Менеджер | K5: январь | L5: февраль | M5: март | N5: апрель | O5: май | P5: Общий итог
A6: Иванов | B6: апрель | C6: мясо | D6: 100 | E6: 50 | F6: =D6-E6 -> 50 | G6: Россия | I6: молоко | J6: Иванов | M6: 180 | P6: 180
A7: Петров | B7: январь | C7: мясо | D7: 100 | E7: 50 | F7: =D7-E7 -> 50 | G7: Страны СНГ | J7: Петров | M7: 270 | P7: 270
A8: Петров | B8: февраль | C8: мясо | D8: 100 | E8: 50 | F8: =D8-E8 -> 50 | G8: Страны СНГ | J8: Сидоров | M8: 50 | P8: 50
A9: Петров | B9: февраль | C9: мясо | D9: 100 | E9: 50 | F9: =D9-E9 -> 50 | G9: Страны СНГ | I9: молоко Итог | M9: 500 | P9: 500
A10: Петров | B10: апрель | C10: мясо | D10: 100 | E10: 50 | F10: =D10-E10 -> 50 | G10: Страны СНГ | I10: мясо | J10: Иванов | K10: 50 | L10: 100 | N10: 100 | P10: 250
A11: Петров | B11: апрель | C11: мясо | D11: 100 | E11: 50 | F11: =D11-E11 -> 50 | G11: Страны СНГ | J11: Петров | K11: 50 | L11: 100 | N11: 100 | P11: 250
A12: Сидоров | B12: май | C12: рыба | D12: 100 | E12: 50 | F12: =D12-E12 -> 50 | G12: Страны СНГ | I12: мясо Итог | K12: 100 | L12: 200 | N12: 200 | P12: 500
A13: Сидоров | B13: январь | C13: рыба | D13: 100 | E13: 50 | F13: =D13-E13 -> 50 | G13: Россия | I13: рыба | J13: Иванов | L13: 50 | P13: 50
A14: Иванов | B14: февраль | C14: рыба | D14: 100 | E14: 50 | F14: =D14-E14 -> 50 | G14: Россия | J14: Сидоров | K14: 50 | O14: 50 | P14: 100
A15: Иванов | B15: март | C15: молоко | D15: 200 | E15: 20 | F15: =D15-E15 -> 180 | G15: Россия | I15: рыба Итог | K15: 50 | L15: 50 | O15: 50 | P15: 150
A16: Петров | B16: март | C16: молоко | D16: 300 | E16: 30 | F16: =D16-E16 -> 270 | G16: Страны СНГ
A17: Сидоров | B17: март | C17: молоко | D17: 150 | E17: 100 | F17: =D17-E17 -> 50 | G17: Страны СНГ

Sheet Лаб5 2
A1: Регион | B1: (Все)
A3: Сумма по полю Прибыль | B3: Месяц
A4: Продукты | B4: Первый | C4: Второй | D4: Общий итог
A5: молоко | B5: 500 | D5: 500
A6: Иванов | B6: 180 | D6: 180
A7: Петров | B7: 270 | D7: 270
A8: Сидоров | B8: 50 | D8: 50
A9: мясо | B9: 300 | C9: 200 | D9: 500
A10: Иванов | B10: 150 | C10: 100 | D10: 250
A11: Петров | B11: 150 | C11: 100 | D11: 250
A12: рыба | B12: 100 | C12: 50 | D12: 150
A13: Иванов | B13: 50 | D13: 50
A14: Сидоров | B14: 50 | C14: 50 | D14: 100
A15: Общий итог | B15: 900 | C15: 250 | D15: 1150

Sheet Лаб5 3
A1: Регион | B1: (Все)
A3: Сумма по полю Прибыль | B3: Месяц
A4: Продукты | B4: январь | C4: февраль | D4: март | E4: апрель | F4: май | G4: Общий итог
A5: молоко | D5: 500 | G5: 500
A6: Иванов | D6: 180 | G6: 180
A7: Петров | D7: 270 | G7: 270
A8: Сидоров | D8: 50 | G8: 50
A9: мясо | B9: 100 | C9: 200 | E9: 200 | G9: 500
A10: Иванов | B10: 50 | C10: 100 | E10: 100 | G10: 250
A11: Петров | B11: 50 | C11: 100 | E11: 100 | G11: 250
A12: рыба | B12: 50 | C12: 50 | F12: 50 | G12: 150
A13: Иванов | C13: 50 | G13: 50
A14: Сидоров | B14: 50 | F14: 50 | G14: 100
A15: Общий итог | B15: 150 | C15: 250 | D15: 500 | E15: 200 | F15: 50 | G15: 1150

Sheet Лаб 5 4
A1: Фамилия | B1: БАЛЛ
A2: Тигр | B2: 0
A3: Петров | B3: 4 | D3: Названия строк | E3: Количество по полю Фамилия
A4: Пупа | B4: 6 | D4: 0-4 | E4: 12
A5: Петров | B5: 2 | D5: 5-9 | E5: 16
A6: Лупа | B6: 5 | D6: Общий итог | E6: 28
A7: Андрей | B7: 9
A8: Губка | B8: 7
A9: Гейрасим | B9: 5
A10: Конституция | B10: 4
A11: Россия | B11: 2
A12: Козлов | B12: 3
A13: Intel XEON | B13: 0
A14: Ершова | B14: 1
A15: Петров | B15: 5
A16: Сидоров | B16: 3
A17: Козлов | B17: 8
A18: Симонова | B18: 7
... A29: Райн Гослинг | B29: 8

Sheet Лаб 5 5
A1: Заказ | B1: Название получателя | C1: Наименование товара | D1: Количество упаковок | E1: Цена за | F1: Стоимость заказа
E2: упаковку | I2: Названия столбцов
A3: 10000 | B3: Кафе "Родничок" | C3: Орех грецкий | D3: 10 | E3: 15.95 | F3: =D3*E3 -> 159.5 | H3: Названия строк | I3: Кешью | J3: Орех миндальный | K3: Фундук | L3: Общий итог
A4: 10001 | B4: Ресторан "Диана" | C4: Орех миндальный | D4: 10 | E4: 17.55 | F4: =D4*E4 -> 175.5 | H4: АО "Баранки"
A5: 10002 | B5: ТОО "Подарок" | C5: Набор специй № 1 | D5: 47 | E5: 22.2 | F5: =D5*E5 -> 1043.4 | H5: Сумма по полю Количество упаковок | J5: 13 | L5: 13
A6: 10003 | B6: ТОО "Карпаты" | C6: Набор специй № 2 | D6: 13 | E6: 26 | F6: =D6*E6 -> 338 | H6: Сумма по полю Цена за | J6: 17.55 | L6: 17.55
A7: 10004 | B7: Кафе "Синий закат" | C7: Набор специй № 1 | D7: 45 | E7: 22.2 | F7: =D7*E7 -> 999 | H7: Сумма по полю Стоимость заказа | J7: 228.15 | L7: 228.15
A8: 10005 | B8: Универмаг "Гомель" | C8: Набор специй № 2 | D8: 35 | E8: 25 | F8: =D8*E8 -> 875 | H8: АО "Кленовый лист"
A9: 10006 | B9: Гастроном "Варшава" | C9: Набор специй № 3 | D9: 125 | E9: 31 | F9: =D9*E9 -> 3875 | H9: Сумма по полю Количество упаковок | K9: 22 | L9: 22
A10: 10007 | B10: ТОО "Новость" | C10: Набор специй № 1 | D10: 11 | E10: 23.5 | F10: =D10*E10 -> 258.5 | H10: Сумма по полю Цена за | K10: 21.25 | L10: 21.25
A11: 10008 | B11: АО "Баранки" | C11: Орех миндальный | D11: 13 | E11: 17.55 | F11: =D11*E11 -> 228.15 | H11: Сумма по полю Стоимость заказа | K11: 467.5 | L11: 467.5
A12: 10009 | B12: ТОО "Карпаты" | C12: Набор специй № 3 | D12: 45 | E12: 33.4 | F12: =D12*E12 -> 1503 | H12: АО "Ленточка"
A13: 10010 | B13: Супермаркет "Речицкий" | C13: Набор специй № 3 | D13: 37 | E13: 34.1 | F13: =D13*E13 -> 1261.7 | H13: Сумма по полю Количество упаковок | I13: 18 | L13: 18
A14: 10011 | B14: Универмаг "Кавказский" | C14: Набор специй № 2 | D14: 23 | E14: 25.5 | F14: =D14*E14 -> 586.5 | H14: Сумма по полю Цена за | I14: 12.1 | L14: 12.1
A15: 10012 | B15: Кафе "Победа" | C15: Орех миндальный | D15: 11 | E15: 17.55 | F15: =D15*E15 -> 193.05 | H15: Сумма по полю Стоимость заказа | I15: 217.8 | L15: 217.8
A16: 10013 | B16: Ресторан "Приморский" | C16: Фундук | D16: 15 | E16: 21.75 | F16: =D16*E16 -> 326.25 | H16: Итог Сумма по полю Количество упаковок | I16: 18 | J16: 13 | K16: 22 | L16: 53
A17: 10014 | B17: Ресторан "Пекин" | C17: Орех бразильский | D17: 44 | E17: 48.2 | F17: =D17*E17 -> 2120.8 | H17: Итог Сумма по полю Цена за | I17: 12.1 | J17: 17.55 | K17: 21.25 | L17: 50.9
A18: 10015 | B18: АО "Ленточка" | C18: Кешью | D18: 18 | E18: 12.1 | F18: =D18*E18 -> 217.8 | H18: Итог Сумма по полю Стоимость заказа | I18: 217.8 | J18: 228.15 | K18: 467.5 | L18: 913.45
A19: 10016 | B19: Бар гостиницы "Турист" | C19: Фундук | D19: 11 | E19: 21.75 | F19: =D19*E19 -> 239.25
A20: 10017 | B20: Универмаг "Российский" | C20: Набор специй № 2 | D20: 35 | E20: 25 | F20: =D20*E20 -> 875
A21: 10018 | B21: Ресторан "Бангкок" | C21: Орех бразильский | D21: 30 | E21: 49.1 | F21: =D21*E21 -> 1473
A22: 10019 | B22: ТОО "Прохлада" | C22: Набор специй № 3 | D22: 48 | E22: 33.4 | F22: =D22*E22 -> 1603.2
A23: 10020 | B23: Пиццерия "Италия" | C23: Орех бразильский | D23: 46 | E23: 48.2 | F23: =D23*E23 -> 2217.2
A24: 10021 | B24: Кафе "Ураган" | C24: Орех грецкий | D24: 26 | E24: 15.5 | F24: =D24*E24 -> 403
A25: 10022 | B25: Бар гостиницы "Россия" | C25: Кешью | D25: 11 | E25: 12.3 | F25: =D25*E25 -> 135.3
A26: 10023 | B26: Бар гостиницы "Россия" | C26: Орех грецкий | D26: 16 | E26: 15.95 | F26: =D26*E26 -> 255.2
A27: 10024 | B27: ТОО "Прохлада" | C27: Орех грецкий | D27: 14 | E27: 15.95 | F27: =D27*E27 -> 223.3
A28: 10025 | B28: Ресторан "Природа" | C28: Кешью | D28: 10 | E28: 12.3 | F28: =D28*E28 -> 123
A29: 10026 | B29: Ресторан "Украина" | C29: Набор специй № 1 | D29: 23 | E29: 22.9 | F29: =D29*E29 -> 526.7
A30: 10027 | B30: Универмаг "Слава" | C30: Орех миндальный | D30: 12 | E30: 17.55 | F30: =D30*E30 -> 210.6
... A53: 10050 | B53: Бар "Три ступени" | C53: Орех грецкий | D53: 18 | E53: 15.95 | F53: =D53*E53 -> 287.1

Sheet Лаб 5 Main
A1: Заказ | B1: Название получателя | C1: Наименование товара | D1: Количество упаковок | E1: Цена за | F1: Стоимость заказа
E2: упаковку
A3: 10000 | B3: Кафе "Родничок" | C3: Орех грецкий | D3: 10 | E3: 15.95 | F3: =D3*E3 -> 159.5
A4: 10001 | B4: Ресторан "Диана" | C4: Орех миндальный | D4: 10 | E4: 17.55 | F4: =D4*E4 -> 175.5
A5: 10002 | B5: ТОО "Подарок" | C5: Набор специй № 1 | D5: 47 | E5: 22.2 | F5: =D5*E5 -> 1043.4
A6: 10003 | B6: ТОО "Карпаты" | C6: Набор специй № 2 | D6: 13 | E6: 26 | F6: =D6*E6 -> 338
A7: 10004 | B7: Кафе "Синий закат" | C7: Набор специй № 1 | D7: 45 | E7: 22.2 | F7: =D7*E7 -> 999
A8: 10005 | B8: Универмаг "Гомель" | C8: Набор специй № 2 | D8: 35 | E8: 25 | F8: =D8*E8 -> 875
A9: 10006 | B9: Гастроном "Варшава" | C9: Набор специй № 3 | D9: 125 | E9: 31 | F9: =D9*E9 -> 3875
A10: 10007 | B10: ТОО "Новость" | C10: Набор специй № 1 | D10: 11 | E10: 23.5 | F10: =D10*E10 -> 258.5
A11: 10008 | B11: АО "Баранки" | C11: Орех миндальный | D11: 13 | E11: 17.55 | F11: =D11*E11 -> 228.15
A12: 10009 | B12: ТОО "Карпаты" | C12: Набор специй № 3 | D12: 45 | E12: 33.4 | F12: =D12*E12 -> 1503
A13: 10010 | B13: Супермаркет "Речицкий" | C13: Набор специй № 3 | D13: 37 | E13: 34.1 | F13: =D13*E13 -> 1261.7
A14: 10011 | B14: Универмаг "Кавказский" | C14: Набор специй № 2 | D14: 23 | E14: 25.5 | F14: =D14*E14 -> 586.5
A15: 10012 | B15: Кафе "Победа" | C15: Орех миндальный | D15: 11 | E15: 17.55 | F15: =D15*E15 -> 193.05
A16: 10013 | B16: Ресторан "Приморский" | C16: Фундук | D16: 15 | E16: 21.75 | F16: =D16*E16 -> 326.25 | J16: Названия строк | K16: Минимум по полю Количество упаковок | L16: Среднее по полю Цена за | M16: Максимум по полю Стоимость заказа
A17: 10014 | B17: Ресторан "Пекин" | C17: Орех бразильский | D17: 44 | E17: 48.2 | F17: =D17*E17 -> 2120.8 | J17: Кафе "Победа" | K17: 11 | L17: 17.55 | M17: 193.05
A18: 10015 | B18: АО "Ленточка" | C18: Кешью | D18: 18 | E18: 12.1 | F18: =D18*E18 -> 217.8 | J18: Орех миндальный | K18: 11 | L18: 17.55 | M18: 193.05
A19: 10016 | B19: Бар гостиницы "Турист" | C19: Фундук | D19: 11 | E19: 21.75 | F19: =D19*E19 -> 239.25 | J19: Кафе "Родничок" | K19: 10 | L19: 15.95 | M19: 159.5
A20: 10017 | B20: Универмаг "Российский" | C20: Набор специй № 2 | D20: 35 | E20: 25 | F20: =D20*E20 -> 875 | J20: Орех грецкий | K20: 10 | L20: 15.95 | M20: 159.5
A21: 10018 | B21: Ресторан "Бангкок" | C21: Орех бразильский | D21: 30 | E21: 49.1 | F21: =D21*E21 -> 1473 | J21: Кафе "Синий закат" | K21: 42 | L21: 23.1 | M21: 1008
A22: 10019 | B22: ТОО "Прохлада" | C22: Набор специй № 3 | D22: 48 | E22: 33.4 | F22: =D22*E22 -> 1603.2 | J22: Набор специй № 1 | K22: 45 | L22: 22.2 | M22: 999
A23: 10020 | B23: Пиццерия "Италия" | C23: Орех бразильский | D23: 46 | E23: 48.2 | F23: =D23*E23 -> 2217.2 | J23: Набор специй № 2 | K23: 42 | L23: 24 | M23: 1008
A24: 10021 | B24: Кафе "Ураган" | C24: Орех грецкий | D24: 26 | E24: 15.5 | F24: =D24*E24 -> 403 | J24: Кафе "Ураган" | K24: 26 | L24: 24.1 | M24: 1962
A25: 10022 | B25: Бар гостиницы "Россия" | C25: Кешью | D25: 11 | E25: 12.3 | F25: =D25*E25 -> 135.3 | J25: Набор специй № 3 | K25: 60 | L25: 32.7 | M25: 1962
A26: 10023 | B26: Бар гостиницы "Россия" | C26: Орех грецкий | D26: 16 | E26: 15.95 | F26: =D26*E26 -> 255.2 | J26: Орех грецкий | K26: 26 | L26: 15.5 | M26: 403
A27: 10024 | B27: ТОО "Прохлада" | C27: Орех грецкий | D27: 14 | E27: 15.95 | F27: =D27*E27 -> 223.3
A28: 10025 | B28: Ресторан "Природа" | C28: Кешью | D28: 10 | E28: 12.3 | F28: =D28*E28 -> 123
A29: 10026 | B29: Ресторан "Украина" | C29: Набор специй № 1 | D29: 23 | E29: 22.9 | F29: =D29*E29 -> 526.7
A30: 10027 | B30: Универмаг "Слава" | C30: Орех миндальный | D30: 12 | E30: 17.55 | F30: =D30*E30 -> 210.6
A31: 10028 | B31: Фирма "Аркада" | C31: Кешью | D31: 14 | E31: 12.3 | F31: =D31*E31 -> 172.2
A32: 10029 | B32: АО "Кленовый лист" | C32: Фундук | D32: 22 | E32: 21.25 | F32: =D32*E32 -> 467.5
A33: 10030 | B33: Пиццерия "Славяне" | C33: Орех миндальный | D33: 10 | E33: 17.55 | F33: =D33*E33 -> 175.5
A34: 10031 | B34: Универмаг "Кавказский" | C34: Набор специй № 3 | D34: 37 | E34: 34.1 | F34: =D34*E34 -> 1261.7
A35: 10032 | B35: Кафе "Синий закат" | C35: Набор специй № 2 | D35: 42 | E35: 24 | F35: =D35*E35 -> 1008
A36: 10033 | B36: Фирма "Браво" | C36: Орех грецкий | D36: 18 | E36: 15.95 | F36: =D36*E36 -> 287.1
A37: 10034 | B37: Ресторан "Диана" | C37: Кешью | D37: 12 | E37: 12.3 | F37: =D37*E37 -> 147.6
A38: 10035 | B38: Магазин "Русский лес" | C38: Фундук | D38: 17 | E38: 21.75 | F38: =D38*E38 -> 369.75
... A53: 10050 | B53: Бар "Три ступени" | C53: Орех грецкий | D53: 18 | E53: 15.95 | F53: =D53*E53 -> 287.1

Sheet Продажа
A1: Продажа товаров
A2: Товар | B2: Кол-во, ед. | C2: Цена, руб. | D2: Стоимость, руб.
A3: Ведро | B3: 2 | C3: =IFERROR(VLOOKUP(A3,Цена!$A$1:$C$20,3,0),FALSE) -> 120 | D3: =C3 * B3 -> 240
A4: Стол | B4: 1 | C4: =IFERROR(VLOOKUP(A4,Цена!$A$1:$C$20,3,0),FALSE) -> 1522 | D4: =C4 * B4 -> 1522
A5: Ершик | B5: 2 | C5: =IFERROR(VLOOKUP(A5,Цена!$A$1:$C$20,3,0),FALSE) -> 70 | D5: =C5 * B5 -> 140
A6: Губка | B6: 5 | C6: =IFERROR(VLOOKUP(A6,Цена!$A$1:$C$20,3,0),FALSE) -> 33 | D6: =C6 * B6 -> 165
A7: Ведро | B7: 5 | C7: =IFERROR(VLOOKUP(A7,Цена!$A$1:$C$20,3,0),FALSE) -> 120 | D7: =C7 * B7 -> 600
A8: Ведро | B8: 4 | C8: =IFERROR(VLOOKUP(A8,Цена!$A$1:$C$20,3,0),FALSE) -> 120 | D8: =C8 * B8 -> 480
A9: Губка | B9: 10 | C9: =IFERROR(VLOOKUP(A9,Цена!$A$1:$C$20,3,0),FALSE) -> 33 | D9: =C9 * B9 -> 330
A10: Стол | B10: 1 | C10: =IFERROR(VLOOKUP(A10,Цена!$A$1:$C$20,3,0),FALSE) -> 1522 | D10: =C10 * B10 -> 1522
A11: Контейнер | B11: 2 | C11: =IFERROR(VLOOKUP(A11,Цена!$A$1:$C$20,3,0),FALSE) -> 214 | D11: =C11 * B11 -> 428
A12: Контейнер | B12: 5 | C12: =IFERROR(VLOOKUP(A12,Цена!$A$1:$C$20,3,0),FALSE) -> 214 | D12: =C12 * B12 -> 1070
A13: Ершик | B13: 20 | C13: =IFERROR(VLOOKUP(A13,Цена!$A$1:$C$20,3,0),FALSE) -> 70 | D13: =C13 * B13 -> 1400
A14: Лента | B14: 1 | C14: =IFERROR(VLOOKUP(A14,Цена!$A$1:$C$20,3,0),FALSE) -> 561 | D14: =C14 * B14 -> 561
... A27: Карандаш | B27: 6 | C27: =IFERROR(VLOOKUP(A27,Цена!$A$1:$C$20,3,0),FALSE) -> 186 | D27: =C27 * B27 -> 1116
D28: =SUM(D3:D27) -> 37509

Sheet Цена
A1: Цены товаров
A2: Товар | B2: Артикул | C2: Цена, руб.
A3: Ведро | B3: 8048 | C3: 120
A4: Веник | B4: 17985 | C4: 52
A5: Губка | B5: 6085 | C5: 33
A6: Стол | B6: 78104 | C6: 1522
A7: Стул | B7: 444 | C7: 525
A8: Табурет | B8: 105580 | C8: 185
A9: Ершик | B9: 3130 | C9: 70
A10: Изолента | B10: 78144 | C10: 254
A11: Указатель | B11: 132691 | C11: 302
A12: Лента | B12: 107521 | C12: 561
A13: Ковер | B13: 44949 | C13: 1962
A14: Контейнер | B14: 78099 | C14: 214
... A20: Карандаш | B20: 87421 | C20: 186

Sheet ГПР
A1: Продажа фруктов | F1: Цены фруктов
A2: Наименование | B2: Вес, кг | C2: Цена, р. | D2: Стоимость, р. | F2: Наименование | G2: Цена, р.
A3: Яблоки | B3: 60 | F3: Абрикос | G3: 40
A4: Груши | B4: 40 | F4: Ананас | G4: 120
A5: Мандарины | B5: 45 | F5: Баклажан | G5: 29
A6: Киви | B6: 23 | F6: Банан | G6: 22
A7: Киви | B7: 60 | F7: Грейпфрут | G7: 45
A8: Ананас | B8: 10 | F8: Груши | G8: 38
A9: Манго | B9: 15 | F9: Киви | G9: 60
A10: Грейпфрут | B10: 14 | F10: Манго | G10: 80
A11: Банан | B11: 48 | F11: Мандарины | G11: 45
A12: Киви | B12: 15 | F12: Нектарин | G12: 40
A13: Киви | B13: 13 | F13: Персик | G13: 45
A14: Персик | B14: 42 | F14: Яблоки | G14: 23
A15: Абрикос | B15: 26 | F15: Абрикос | G15: 40
A16: Нектарин | B16: 14
A23: Наименование | B23: Яблоки | C23: Груши | D23: Мандарины | E23: Киви | F23: Киви | G23: Ананас | H23: Манго | I23: Грейпфрут | J23: Банан | K23: Киви | L23: Киви | M23: Персик | N23: Абрикос | O23: Нектарин
A24: Вес, кг | B24: 60 | C24: 40 | D24: 45 | E24: 23 | F24: 60 | G24: 10 | H24: 15 | I24: 14 | J24: 48 | K24: 15 | L24: 13 | M24: 42 | N24: 26 | O24: 14
A25: Цена, р. | B25: =HLOOKUP(B23,$A$29:$M$30,2,0) -> 23 | C25: =HLOOKUP(C23,$A$29:$M$30,2,0) -> 38 | D25: =HLOOKUP(D23,$A$29:$M$30,2,0) -> 45 | E25: =HLOOKUP(E23,$A$29:$M$30,2,0) -> 60 | F25: =HLOOKUP(F23,$A$29:$M$30,2,0) -> 60 | G25: =HLOOKUP(G23,$A$29:$M$30,2,0) -> 120 | H25: =HLOOKUP(H23,$A$29:$M$30,2,0) -> 80 | I25: =HLOOKUP(I23,$A$29:$M$30,2,0) -> 45 | ... O25: =HLOOKUP(O23,$A$29:$M$30,2,0) -> 40
A26: Стоимость, р. | B26: =B25 * B24 -> 1380 | C26: =C25 * C24 -> 1520 | D26: =D25 * D24 -> 2025 | E26: =E25 * E24 -> 1380 | F26: =F25 * F24 -> 3600 | G26: =G25 * G24 -> 1200 | H26: =H25 * H24 -> 1200 | I26: =I25 * I24 -> 630 | ... O26: =O25 * O24 -> 560 | P26: =SUM(B26:O26) -> 19161
A29: Наименование | B29: Абрикос | C29: Ананас | D29: Баклажан | E29: Банан | F29: Грейпфрут | G29: Груши | H29: Киви | I29: Манго | J29: Мандарины | K29: Нектарин | L29: Персик | M29: Яблоки | N29: Абрикос
A30: Цена, р. | B30: 40 | C30: 120 | D30: 29 | E30: 22 | F30: 45 | G30: 38 | H30: 60 | I30: 80 | J30: 45 | K30: 40 | L30: 45 | M30: 23 | N30: 40

Sheet Прайс 2019 г.
A1: Прайс 2019 г.
A2: Артикул | B2: Наименование | C2: Стоимость, р. | D2: Новая стоимость, р.
A3: 123-432 | B3: Корпус редуктора | C3: 200 | D3: =VLOOKUP(A3,'Прайс 2020 г.'!$A$1:$C$10,3,0) -> 250
A4: 332-554 | B4: Шестерня 1 передачи | C4: 43 | D4: =VLOOKUP(A4,'Прайс 2020 г.'!$A$1:$C$10,3,0) -> 50
A5: 642-443 | B5: Привод вала | C5: 75 | D5: =VLOOKUP(A5,'Прайс 2020 г.'!$A$1:$C$10,3,0) -> 85
A6: 322-341 | B6: Шестерня 2 передачи | C6: 55 | D6: =VLOOKUP(A6,'Прайс 2020 г.'!$A$1:$C$10,3,0) -> 60
A7: 444-321 | B7: Накладка корпуса | C7: 76 | D7: =VLOOKUP(A7,'Прайс 2020 г.'!$A$1:$C$10,3,0) -> 80
A8: 664-313 | B8: Коробка передач в сборе | C8: 435 | D8: =VLOOKUP(A8,'Прайс 2020 г.'!$A$1:$C$10,3,0) -> 450
A9: 785-567 | B9: Сцепление | C9: 500 | D9: =VLOOKUP(A9,'Прайс 2020 г.'!$A$1:$C$10,3,0) -> 500

Sheet Прайс 2020 г.
A1: Прайс 2020 г.
A2: Артикул | B2: Наименование | C2: Новая стоимость, р.
A3: 332-554 | B3: Шестерня 1 передачи | C3: 50
A4: 123-432 | B4: Корпус редуктора | C4: 250
A5: 444-321 | B5: Накладка корпуса | C5: 80
A6: 642-443 | B6: Привод вала | C6: 85
A7: 322-341 | B7: Шестерня 2 передачи | C7: 60
A8: 664-313 | B8: Коробка передач в сборе | C8: 450
A9: 785-567 | B9: Сцепление | C9: 500
A10: 986-334 | B10: Тормозной цилиндр | C10: 280

Sheet Оценки
A1: Предмет | B1: Алгебра | C1: Геометрия | D1: Физика | E1: Химия | F1: Информатика | G1: История | H1: География
A2: Оценка | B2: 5 | C2: 4 | D2: 2 | E2: 3 | F2: 1 | G2: 4 | H2: 2
A5: Введите предмет | B5: Физика
A6: Оценка | B6: =HLOOKUP(B5,$A$1:$H$2,2,0) -> 2

Sheet Справочники
A1: № комнаты | B1: Тип комнаты | D1: Тип комнаты | E1: Цена в долларах | G1: Курс доллара: | H1: 101.85
A2: 101 | B2: Однокомн | D2: Однокомн | E2: 110
A3: 102 | B3: Однокомн | D3: Люкс | E3: 200 | G3: Скидка: | H3: 0.05 | K3: Скидка: | L3: 0.05
A4: 103 | B4: Однокомн | D4: Двухкомн | E4: 150 | G4: Дней не менее | H4: 9 | K4: Дней до 9 | L4: 9
A5: 104 | B5: Люкс
A6: 105 | B6: Двухкомн | K6: Скидка: | L6: 0.1
A7: 106 | B7: Двухкомн | K7: Дней от 9 до 15 | L7: 15
A8: 107 | B8: Двухкомн
A9: 201 | B9: Двухкомн
A10: 202 | B10: Люкс
A11: 203 | B11: Люкс
A12: 204 | B12: Люкс
A13: 205 | B13: Однокомн
A14: 206 | B14: Однокомн
A15: 207 | B15: Однокомн
A16: 208 | B16: Однокомн

Sheet Расчёт
A1: N п/п | B1: ФИО | C1: № комнаты | D1: Тип комнаты | E1: Продолжительность пребывания в днях | F1: Стоимость проживания за 1 день | H1: К оплате, в руб.
F2: в долл. | G2: в руб.
A3: 1 | B3: Иванов А.И. | C3: 104 | D3: =VLOOKUP(C3,Комнаты,2,0) -> Люкс | E3: 10 | F3: =VLOOKUP(D3,Цены,2,0) -> 200 | G3: =F3*Курс_доллара -> 20370 | H3: =G3*E3 -> 203700
A4: 2 | B4: Иваненко М.Р. | C4: 201 | D4: =VLOOKUP(C4,Комнаты,2,0) -> Двухкомн | E4: 9 | F4: =VLOOKUP(D4,Цены,2,0) -> 150 | G4: =F4*Курс_доллара -> 15277.5 | H4: =G4*E4 -> 137497.5
A5: 3 | B5: Петров Т.А. | C5: 203 | D5: =VLOOKUP(C5,Комнаты,2,0) -> Люкс | E5: 6 | F5: =VLOOKUP(D5,Цены,2,0) -> 200 | G5: =F5*Курс_доллара -> 20370 | H5: =G5*E5 -> 122220
A6: 4 | B6: Петренко П.П. | C6: 106 | D6: =VLOOKUP(C6,Комнаты,2,0) -> Двухкомн | E6: 7 | F6: =VLOOKUP(D6,Цены,2,0) -> 150 | G6: =F6*Курс_доллара -> 15277.5 | H6: =G6*E6 -> 106942.5
A7: 5 | B7: Сидоров В.К | C7: 202 | D7: =VLOOKUP(C7,Комнаты,2,0) -> Люкс | E7: 5 | F7: =VLOOKUP(D7,Цены,2,0) -> 200 | G7: =F7*Курс_доллара -> 20370 | H7: =G7*E7 -> 101850
A8: 6 | B8: Седова К.У. | C8: 208 | D8: =VLOOKUP(C8,Комнаты,2,0) -> Однокомн | E8: 18 | F8: =VLOOKUP(D8,Цены,2,0) -> 110 | G8: =F8*Курс_доллара -> 11203.5 | H8: =G8*E8 -> 201663
A9: 7 | B9: Фомичев А.Л. | C9: 205 | D9: =VLOOKUP(C9,Комнаты,2,0) -> Однокомн | E9: 6 | F9: =VLOOKUP(D9,Цены,2,0) -> 110 | G9: =F9*Курс_доллара -> 11203.5 | H9: =G9*E9 -> 67221

Sheet Упражнение 1
A1: N п/п | B1: ФИО | C1: № комнаты | D1: Тип комнаты | E1: Продолжительность пребывания в днях | F1: Стоимость проживания за 1 день | H1: К оплате, в руб.
F2: в долл. | G2: в руб.
A3: 1 | B3: Иванов А.И. | C3: 104 | D3: =VLOOKUP(C3,Комнаты,2,0) -> Люкс | E3: 100 | F3: =VLOOKUP(D3,Цены,2,0) -> 200 | G3: =F3*Курс_доллара -> 20370 | H3: =IF((E3>=0),IF(E3<Дней_мин,G3*E3*(1-Дней_мин_скидка),IF(AND(E3>=Дней_мин,E3<=Дней_макс),G3*E3*(1-Дней_макс_скидка), "Скидки не будет(((ъ")), 0) -> Скидки не будет(((ъ
A4: 2 | B4: Иваненко М.Р. | C4: 201 | D4: =VLOOKUP(C4,Комнаты,2,0) -> Двухкомн | E4: 9 | F4: =VLOOKUP(D4,Цены,2,0) -> 150 | G4: =F4*Курс_доллара -> 15277.5 | H4: =IF((E4>=0),IF(E4<Дней_мин,G4*E4*(1-Дней_мин_скидка),IF(AND(E4>=Дней_мин,E4<=Дней_макс),G4*E4*(1-Дней_макс_скидка), "Скидки не будет(((ъ")), 0) -> 123747.75
A5: 3 | B5: Петров Т.А. | C5: 203 | D5: =VLOOKUP(C5,Комнаты,2,0) -> Люкс | E5: 6 | F5: =VLOOKUP(D5,Цены,2,0) -> 200 | G5: =F5*Курс_доллара -> 20370 | H5: =IF((E5>=0),IF(E5<Дней_мин,G5*E5*(1-Дней_мин_скидка),IF(AND(E5>=Дней_мин,E5<=Дней_макс),G5*E5*(1-Дней_макс_скидка), "Скидки не будет(((ъ")), 0) -> 116109
A6: 4 | B6: Петренко П.П. | C6: 106 | D6: =VLOOKUP(C6,Комнаты,2,0) -> Двухкомн | E6: 7 | F6: =VLOOKUP(D6,Цены,2,0) -> 150 | G6: =F6*Курс_доллара -> 15277.5 | H6: =IF((E6>=0),IF(E6<Дней_мин,G6*E6*(1-Дней_мин_скидка),IF(AND(E6>=Дней_мин,E6<=Дней_макс),G6*E6*(1-Дней_макс_скидка), "Скидки не будет(((ъ")), 0) -> 101595.38
A7: 5 | B7: Сидоров В.К | C7: 202 | D7: =VLOOKUP(C7,Комнаты,2,0) -> Люкс | E7: -5 | F7: =VLOOKUP(D7,Цены,2,0) -> 200 | G7: =F7*Курс_доллара -> 20370 | H7: =IF((E7>=0),IF(E7<Дней_мин,G7*E7*(1-Дней_мин_скидка),IF(AND(E7>=Дней_мин,E7<=Дней_макс),G7*E7*(1-Дней_макс_скидка), "Скидки не будет(((ъ")), 0) -> 0
A8: 6 | B8: Седова К.У. | C8: 208 | D8: =VLOOKUP(C8,Комнаты,2,0) -> Однокомн | E8: 18 | F8: =VLOOKUP(D8,Цены,2,0) -> 110 | G8: =F8*Курс_доллара -> 11203.5 | H8: =IF((E8>=0),IF(E8<Дней_мин,G8*E8*(1-Дней_мин_скидка),IF(AND(E8>=Дней_мин,E8<=Дней_макс),G8*E8*(1-Дней_макс_скидка), "Скидки не будет(((ъ")), 0) -> Скидки не будет(((ъ
A9: 7 | B9: Фомичев А.Л. | C9: 205 | D9: =VLOOKUP(C9,Комнаты,2,0) -> Однокомн | E9: 6 | F9: =VLOOKUP(D9,Цены,2,0) -> 110 | G9: =F9*Курс_доллара -> 11203.5 | H9: =IF((E9>=0),IF(E9<Дней_мин,G9*E9*(1-Дней_мин_скидка),IF(AND(E9>=Дней_мин,E9<=Дней_макс),G9*E9*(1-Дней_макс_скидка), "Скидки не будет(((ъ")), 0) -> 63859.95
